coreason_human_layer/__init__.py
coreason_human_layer/archiver.py
coreason_human_layer/branch_manager.py
coreason_human_layer/gateways.py
coreason_human_layer/main.py
coreason_human_layer/models.py
coreason_human_layer/server.py
coreason_human_layer/stasis.py
coreason_human_layer/utils/__init__.py
coreason_human_layer/utils/formatter.py
coreason_human_layer/utils/logger.py
coreason_human_layer-0.4.0.dist-info/METADATA
coreason_human_layer-0.4.0.dist-info/WHEEL
coreason_human_layer-0.4.0.dist-info/licenses/LICENSE
coreason_human_layer-0.4.0.dist-info/licenses/NOTICE
coreason_human_layer-0.4.0.dist-info/RECORD
