Metadata-Version: 2.4
Name: coreason_human_layer
Version: 0.4.0
Summary: coreason-human-layer
License: # The Prosperity Public License 3.0.0
License-File: LICENSE
License-File: NOTICE
Author: Gowtham A Rao
Author-email: gowtham.rao@coreason.ai
Requires-Python: >=3.11
Classifier: License :: Other/Proprietary License
Classifier: Programming Language :: Python :: 3.12
Classifier: Operating System :: OS Independent
Requires-Dist: aiofiles (>=25.1.0,<26.0.0)
Requires-Dist: anyio (>=4.12.1,<5.0.0)
Requires-Dist: boto3 (>=1.42.37,<2.0.0)
Requires-Dist: coreason-identity (>=0.4.2,<0.5.0)
Requires-Dist: fastapi (>=0.115.0,<0.116.0)
Requires-Dist: httpx (>=0.28.1,<0.29.0)
Requires-Dist: loguru (>=0.7.3,<0.8.0)
Requires-Dist: pydantic (>=2.12.5,<3.0.0)
Requires-Dist: redis (>=7.1.0,<8.0.0)
Requires-Dist: requests (>=2.32.5,<3.0.0)
Requires-Dist: uvicorn (>=0.27.0,<0.28.0)
Project-URL: Documentation, https://github.com/CoReason-AI/coreason_human_layer
Project-URL: Homepage, https://github.com/CoReason-AI/coreason_human_layer
Project-URL: Repository, https://github.com/CoReason-AI/coreason_human_layer
